{
  "id": "adventureitemnames:rickandmorty_creatures",
  "entries": [
    { "text": "Time Skater" },
    { "text": "Hamster-People" },
    { "text": "Cone-Headed Ones" },
    { "text": "Cronenberg" },
    { "text": "Phoenix-Person" },
    { "text": "Council Mortys" },
    { "text": "Galaxy-Federation Bugs" },
    { "text": "Plumbus Heeblers" },
    { "text": "Squanch Beasts" },
    { "text": "Story Lord" },
    { "text": "Greebybobe" },
    { "text": "Glootie" },
    { "text": "Vat-of-Acid Survivors" },
    { "text": "Snuffles Pack" },
    { "text": "Meeseeks" },
    { "text": "Cromulon" },
    { "text": "Gazorpazorps" },
    { "text": "Gromflomites" },
    { "text": "Glip Glops" },
    { "text": "Reverse Giraffe" },
    { "text": "Memory Parasites" },
    { "text": "Telepathic Spider" },
    { "text": "Eyeholes" },
    { "text": "Mr. Frundles" },
    { "text": "Death Stalkers" },
    { "text": "Schleemypoo" },
    { "text": "Cat People" },
    { "text": "Sleepy Gary" },
    { "text": "Photon-Beings" },
    { "text": "Microverse Citizen" }
  ]
}
