{
  "id": "adventureitemnames:adventuretime_elements",
  "entries": [
    { "text": "Mathematical!" },
    { "text": "Algebraic!" },
    { "text": "Glob" },
    { "text": "Grod" },
    { "text": "Gob" },
    { "text": "the Mushroom War" },
    { "text": "Time Travel" },
    { "text": "Wizardry" },
    { "text": "Vampirism" },
    { "text": "the Lich's Curse" },
    { "text": "Crown Magic" },
    { "text": "the Catalyst Comet" },
    { "text": "Wishing" },
    { "text": "the Cosmic Order" },
    { "text": "Dream Magic" },
    { "text": "the Goo Realm" },
    { "text": "the Ice Crown" },
    { "text": "the Vault" },
    { "text": "Wild Magic" },
    { "text": "the Doomsday Bomb" },
    { "text": "the Enchiridion" },
    { "text": "the Demon Sword" }
  ]
}
